[
  {
    "file": "1.jpg",
    "name": ", Dziwny ogród",
    "author": "J. Mehoffer",
    "year": "1903"
  },
  {
    "file": "2.jpg",
    "name": "Hamlet polski - Portret Aleksandra Wielopolskiego",
    "author": "J. Malczewski",
    "year": "1903"
  },
  {
    "file": "3.jpg",
    "name": "My i wojna",
    "author": "E. Okuń",
    "year": "1917-1923"
  },
  {
    "file": "4.jpg",
    "name": "Portret żony artysty Teodory z Giebułtowskich",
    "author": "J. Matejko",
    "year": "1879"
  },
  {
    "file": "5.jpg",
    "name": "Autoportret",
    "author": "J. Fałat",
    "year": "1896"
  },
  {
    "file": "6.jpg",
    "name": "Portret Hieronima Floriana Radziwiłła",
    "author": "J. Wessel",
    "year": "1745/46"
  },
  {
    "file": "7.jpg",
    "name": "Autoportret",
    "author": "S. J. Witkiewicz",
    "year": "1913"
  },
  {
    "file": "8.jpg",
    "name": "Melodia",
    "author": "M. Jabłoński",
    "year": "1926"
  }
]
